dojo_mysql/__init__.py
dojo_mysql/source.py
dojo_mysql/beam/__init__.py
dojo_mysql/beam/source.py
dojo_mysql-0.0.29.dist-info/DESCRIPTION.rst
dojo_mysql-0.0.29.dist-info/METADATA
dojo_mysql-0.0.29.dist-info/RECORD
dojo_mysql-0.0.29.dist-info/WHEEL
dojo_mysql-0.0.29.dist-info/metadata.json
dojo_mysql-0.0.29.dist-info/top_level.txt
