Metadata-Version: 2.0
Name: dojo-mysql
Version: 0.0.29
Summary: Dojo source and sink adapters for MySQL connections.
Home-page: https://dojo.dataup.me/
Author: Data Up
Author-email: dojo@dataup.me
License: UNKNOWN
Platform: UNKNOWN
Requires-Dist: PyMySQL
Requires-Dist: dojo
